<?xml version="1.0"?>
<ArrayOfToken xmlns:xsi="http://www.w3.org/2001/XMLSchema-instance" xmlns:xsd="http://www.w3.org/2001/XMLSchema">
  <Token>
    <Word>AddHandler</Word>
    <ClassName>keyword</ClassName>
  </Token>
  <Token>
    <Word>AddressOf</Word>
    <ClassName>keyword</ClassName>
  </Token>
  <Token>
    <Word>Alias</Word>
    <ClassName>keyword</ClassName>
  </Token>
  <Token>
    <Word>And</Word>
    <ClassName>keyword</ClassName>
  </Token>
  <Token>
    <Word>AndAlso</Word>
    <ClassName>keyword</ClassName>
  </Token>
  <Token>
    <Word>Ansi</Word>
    <ClassName>keyword</ClassName>
  </Token>
  <Token>
    <Word>As</Word>
    <ClassName>keyword</ClassName>
  </Token>
  <Token>
    <Word>Assembly</Word>
    <ClassName>keyword</ClassName>
  </Token>
  <Token>
    <Word>Auto</Word>
    <ClassName>keyword</ClassName>
  </Token>
  <Token>
    <Word>Boolean</Word>
    <ClassName>keyword</ClassName>
  </Token>
  <Token>
    <Word>ByRef</Word>
    <ClassName>keyword</ClassName>
  </Token>
  <Token>
    <Word>Byte</Word>
    <ClassName>keyword</ClassName>
  </Token>
  <Token>
    <Word>ByVal</Word>
    <ClassName>keyword</ClassName>
  </Token>
  <Token>
    <Word>Call</Word>
    <ClassName>keyword</ClassName>
  </Token>
  <Token>
    <Word>Case</Word>
    <ClassName>keyword</ClassName>
  </Token>
  <Token>
    <Word>Catch</Word>
    <ClassName>keyword</ClassName>
  </Token>
  <Token>
    <Word>CBool</Word>
    <ClassName>keyword</ClassName>
  </Token>
  <Token>
    <Word>CByte</Word>
    <ClassName>keyword</ClassName>
  </Token>
  <Token>
    <Word>CChar</Word>
    <ClassName>keyword</ClassName>
  </Token>
  <Token>
    <Word>CDate</Word>
    <ClassName>keyword</ClassName>
  </Token>
  <Token>
    <Word>CDbl</Word>
    <ClassName>keyword</ClassName>
  </Token>
  <Token>
    <Word>CDec</Word>
    <ClassName>keyword</ClassName>
  </Token>
  <Token>
    <Word>Char</Word>
    <ClassName>keyword</ClassName>
  </Token>
  <Token>
    <Word>CInt</Word>
    <ClassName>keyword</ClassName>
  </Token>
  <Token>
    <Word>Class</Word>
    <ClassName>keyword</ClassName>
  </Token>
  <Token>
    <Word>CLng</Word>
    <ClassName>keyword</ClassName>
  </Token>
  <Token>
    <Word>CObj</Word>
    <ClassName>keyword</ClassName>
  </Token>
  <Token>
    <Word>Const</Word>
    <ClassName>keyword</ClassName>
  </Token>
  <Token>
    <Word>CShort</Word>
    <ClassName>keyword</ClassName>
  </Token>
  <Token>
    <Word>CSng</Word>
    <ClassName>keyword</ClassName>
  </Token>
  <Token>
    <Word>CStr</Word>
    <ClassName>keyword</ClassName>
  </Token>
  <Token>
    <Word>CType</Word>
    <ClassName>keyword</ClassName>
  </Token>
  <Token>
    <Word>Date</Word>
    <ClassName>keyword</ClassName>
  </Token>
  <Token>
    <Word>Decimal</Word>
    <ClassName>keyword</ClassName>
  </Token>
  <Token>
    <Word>Declare</Word>
    <ClassName>keyword</ClassName>
  </Token>
  <Token>
    <Word>Default</Word>
    <ClassName>keyword</ClassName>
  </Token>
  <Token>
    <Word>Delegate</Word>
    <ClassName>keyword</ClassName>
  </Token>
  <Token>
    <Word>Dim</Word>
    <ClassName>keyword</ClassName>
  </Token>
  <Token>
    <Word>DirectCast</Word>
    <ClassName>keyword</ClassName>
  </Token>
  <Token>
    <Word>Do</Word>
    <ClassName>keyword</ClassName>
  </Token>
  <Token>
    <Word>Double</Word>
    <ClassName>keyword</ClassName>
  </Token>
  <Token>
    <Word>Each</Word>
    <ClassName>keyword</ClassName>
  </Token>
  <Token>
    <Word>Else</Word>
    <ClassName>keyword</ClassName>
  </Token>
  <Token>
    <Word>ElseIf</Word>
    <ClassName>keyword</ClassName>
  </Token>
  <Token>
    <Word>End</Word>
    <ClassName>keyword</ClassName>
  </Token>
  <Token>
    <Word>EndIf</Word>
    <ClassName>keyword</ClassName>
  </Token>
  <Token>
    <Word>Enum</Word>
    <ClassName>keyword</ClassName>
  </Token>
  <Token>
    <Word>Erase</Word>
    <ClassName>keyword</ClassName>
  </Token>
  <Token>
    <Word>Error</Word>
    <ClassName>keyword</ClassName>
  </Token>
  <Token>
    <Word>Event</Word>
    <ClassName>keyword</ClassName>
  </Token>
  <Token>
    <Word>Exit</Word>
    <ClassName>keyword</ClassName>
  </Token>
  <Token>
    <Word>False</Word>
    <ClassName>keyword</ClassName>
  </Token>
  <Token>
    <Word>Finally</Word>
    <ClassName>keyword</ClassName>
  </Token>
  <Token>
    <Word>For</Word>
    <ClassName>keyword</ClassName>
  </Token>
  <Token>
    <Word>Friend</Word>
    <ClassName>keyword</ClassName>
  </Token>
  <Token>
    <Word>Function</Word>
    <ClassName>keyword</ClassName>
  </Token>
  <Token>
    <Word>Get</Word>
    <ClassName>keyword</ClassName>
  </Token>
  <Token>
    <Word>GetType</Word>
    <ClassName>keyword</ClassName>
  </Token>
  <Token>
    <Word>GoSub</Word>
    <ClassName>keyword</ClassName>
  </Token>
  <Token>
    <Word>GoTo</Word>
    <ClassName>keyword</ClassName>
  </Token>
  <Token>
    <Word>Handles</Word>
    <ClassName>keyword</ClassName>
  </Token>
  <Token>
    <Word>If</Word>
    <ClassName>keyword</ClassName>
  </Token>
  <Token>
    <Word>Implements</Word>
    <ClassName>keyword</ClassName>
  </Token>
  <Token>
    <Word>Imports</Word>
    <ClassName>keyword</ClassName>
  </Token>
  <Token>
    <Word>In</Word>
    <ClassName>keyword</ClassName>
  </Token>
  <Token>
    <Word>Inherits</Word>
    <ClassName>keyword</ClassName>
  </Token>
  <Token>
    <Word>Integer</Word>
    <ClassName>keyword</ClassName>
  </Token>
  <Token>
    <Word>Interface</Word>
    <ClassName>keyword</ClassName>
  </Token>
  <Token>
    <Word>Is</Word>
    <ClassName>keyword</ClassName>
  </Token>
  <Token>
    <Word>Let</Word>
    <ClassName>keyword</ClassName>
  </Token>
  <Token>
    <Word>Lib</Word>
    <ClassName>keyword</ClassName>
  </Token>
  <Token>
    <Word>Like</Word>
    <ClassName>keyword</ClassName>
  </Token>
  <Token>
    <Word>Long</Word>
    <ClassName>keyword</ClassName>
  </Token>
  <Token>
    <Word>Loop</Word>
    <ClassName>keyword</ClassName>
  </Token>
  <Token>
    <Word>Me</Word>
    <ClassName>keyword</ClassName>
  </Token>
  <Token>
    <Word>Mod</Word>
    <ClassName>keyword</ClassName>
  </Token>
  <Token>
    <Word>Module</Word>
    <ClassName>keyword</ClassName>
  </Token>
  <Token>
    <Word>MustInherit</Word>
    <ClassName>keyword</ClassName>
  </Token>
  <Token>
    <Word>MustOverride</Word>
    <ClassName>keyword</ClassName>
  </Token>
  <Token>
    <Word>MyBase</Word>
    <ClassName>keyword</ClassName>
  </Token>
  <Token>
    <Word>MyClass</Word>
    <ClassName>keyword</ClassName>
  </Token>
  <Token>
    <Word>Namespace</Word>
    <ClassName>keyword</ClassName>
  </Token>
  <Token>
    <Word>New</Word>
    <ClassName>keyword</ClassName>
  </Token>
  <Token>
    <Word>Next</Word>
    <ClassName>keyword</ClassName>
  </Token>
  <Token>
    <Word>Not</Word>
    <ClassName>keyword</ClassName>
  </Token>
  <Token>
    <Word>Nothing</Word>
    <ClassName>keyword</ClassName>
  </Token>
  <Token>
    <Word>NotInheritable</Word>
    <ClassName>keyword</ClassName>
  </Token>
  <Token>
    <Word>NotOverridable</Word>
    <ClassName>keyword</ClassName>
  </Token>
  <Token>
    <Word>Object</Word>
    <ClassName>keyword</ClassName>
  </Token>
  <Token>
    <Word>On</Word>
    <ClassName>keyword</ClassName>
  </Token>
  <Token>
    <Word>Option</Word>
    <ClassName>keyword</ClassName>
  </Token>
  <Token>
    <Word>Optional</Word>
    <ClassName>keyword</ClassName>
  </Token>
  <Token>
    <Word>Or</Word>
    <ClassName>keyword</ClassName>
  </Token>
  <Token>
    <Word>OrElse</Word>
    <ClassName>keyword</ClassName>
  </Token>
  <Token>
    <Word>Overloads</Word>
    <ClassName>keyword</ClassName>
  </Token>
  <Token>
    <Word>Overridable</Word>
    <ClassName>keyword</ClassName>
  </Token>
  <Token>
    <Word>Overrides</Word>
    <ClassName>keyword</ClassName>
  </Token>
  <Token>
    <Word>ParamArray</Word>
    <ClassName>keyword</ClassName>
  </Token>
  <Token>
    <Word>Preserve</Word>
    <ClassName>keyword</ClassName>
  </Token>
  <Token>
    <Word>Private</Word>
    <ClassName>keyword</ClassName>
  </Token>
  <Token>
    <Word>Property</Word>
    <ClassName>keyword</ClassName>
  </Token>
  <Token>
    <Word>Protected</Word>
    <ClassName>keyword</ClassName>
  </Token>
  <Token>
    <Word>Public</Word>
    <ClassName>keyword</ClassName>
  </Token>
  <Token>
    <Word>RaiseEvent</Word>
    <ClassName>keyword</ClassName>
  </Token>
  <Token>
    <Word>ReadOnly</Word>
    <ClassName>keyword</ClassName>
  </Token>
  <Token>
    <Word>ReDim</Word>
    <ClassName>keyword</ClassName>
  </Token>
  <Token>
    <Word>REM</Word>
    <ClassName>keyword</ClassName>
  </Token>
  <Token>
    <Word>RemoveHandler</Word>
    <ClassName>keyword</ClassName>
  </Token>
  <Token>
    <Word>Resume</Word>
    <ClassName>keyword</ClassName>
  </Token>
  <Token>
    <Word>Return</Word>
    <ClassName>keyword</ClassName>
  </Token>
  <Token>
    <Word>Select</Word>
    <ClassName>keyword</ClassName>
  </Token>
  <Token>
    <Word>Set</Word>
    <ClassName>keyword</ClassName>
  </Token>
  <Token>
    <Word>Shadows</Word>
    <ClassName>keyword</ClassName>
  </Token>
  <Token>
    <Word>Shared</Word>
    <ClassName>keyword</ClassName>
  </Token>
  <Token>
    <Word>Short</Word>
    <ClassName>keyword</ClassName>
  </Token>
  <Token>
    <Word>Single</Word>
    <ClassName>keyword</ClassName>
  </Token>
  <Token>
    <Word>Static</Word>
    <ClassName>keyword</ClassName>
  </Token>
  <Token>
    <Word>Step</Word>
    <ClassName>keyword</ClassName>
  </Token>
  <Token>
    <Word>Stop</Word>
    <ClassName>keyword</ClassName>
  </Token>
  <Token>
    <Word>String</Word>
    <ClassName>keyword</ClassName>
  </Token>
  <Token>
    <Word>Structure</Word>
    <ClassName>keyword</ClassName>
  </Token>
  <Token>
    <Word>Sub</Word>
    <ClassName>keyword</ClassName>
  </Token>
  <Token>
    <Word>SyncLock</Word>
    <ClassName>keyword</ClassName>
  </Token>
  <Token>
    <Word>Then</Word>
    <ClassName>keyword</ClassName>
  </Token>
  <Token>
    <Word>Throw</Word>
    <ClassName>keyword</ClassName>
  </Token>
  <Token>
    <Word>To</Word>
    <ClassName>keyword</ClassName>
  </Token>
  <Token>
    <Word>True</Word>
    <ClassName>keyword</ClassName>
  </Token>
  <Token>
    <Word>Try</Word>
    <ClassName>keyword</ClassName>
  </Token>
  <Token>
    <Word>TypeOf</Word>
    <ClassName>keyword</ClassName>
  </Token>
  <Token>
    <Word>Unicode</Word>
    <ClassName>keyword</ClassName>
  </Token>
  <Token>
    <Word>Until</Word>
    <ClassName>keyword</ClassName>
  </Token>
  <Token>
    <Word>Variant</Word>
    <ClassName>keyword</ClassName>
  </Token>
  <Token>
    <Word>Wend</Word>
    <ClassName>keyword</ClassName>
  </Token>
  <Token>
    <Word>When</Word>
    <ClassName>keyword</ClassName>
  </Token>
  <Token>
    <Word>While</Word>
    <ClassName>keyword</ClassName>
  </Token>
  <Token>
    <Word>With</Word>
    <ClassName>keyword</ClassName>
  </Token>
  <Token>
    <Word>WithEvents</Word>
    <ClassName>keyword</ClassName>
  </Token>
  <Token>
    <Word>WriteOnly</Word>
    <ClassName>keyword</ClassName>
  </Token>
  <Token>
    <Word>Xor</Word>
    <ClassName>keyword</ClassName>
  </Token>
</ArrayOfToken>
